gutenfetch/__init__.py
gutenfetch-0.0.5.data/scripts/gutenfetch
gutenfetch-0.0.5.dist-info/DESCRIPTION.rst
gutenfetch-0.0.5.dist-info/METADATA
gutenfetch-0.0.5.dist-info/RECORD
gutenfetch-0.0.5.dist-info/WHEEL
gutenfetch-0.0.5.dist-info/metadata.json
gutenfetch-0.0.5.dist-info/top_level.txt
