Metadata-Version: 2.0
Name: gutenfetch
Version: 0.0.5
Summary: Bulk downloads from project gutenberg.
Home-page: https://github.com/empirical-org/Quill-NLP-Tools-and-Datasets
Author: Quill.org
Author-email: max@quill.org
License: MIT
Platform: UNKNOWN
Requires-Dist: bs4
Requires-Dist: requests
